README.rst
setup.py
ml0/__init__.py
ml0/ml0.py
ml0.egg-info/PKG-INFO
ml0.egg-info/SOURCES.txt
ml0.egg-info/dependency_links.txt
ml0.egg-info/requires.txt
ml0.egg-info/top_level.txt